codefast/__init__.py
codefast/argparser.py
codefast/cn.py
codefast/constants.py
codefast/core.py
codefast/date.py
codefast/ds.py
codefast/exception.py
codefast/logger.py
codefast/math.py
codefast/reader.py
codefast/text.py
codefast/tmp.py
codefast/utils.py
codefast/algorithm/__init__.py
codefast/algorithm/str.py
codefast/asyncio/__init__.py
codefast/asyncio/logger.py
codefast/asyncio/rabbitmq.py
codefast/base/__init__.py
codefast/base/format_print.py
codefast/decorators/__init__.py
codefast/decorators/log.py
codefast/decorators/retry.py
codefast/fio/__init__.py
codefast/fio/ffpb.py
codefast/functools/__init__.py
codefast/functools/random.py
codefast/functools/subroutine.py
codefast/io/__init__.py
codefast/io/_json.py
codefast/io/dblite.py
codefast/io/fdb.py
codefast/io/file.py
codefast/io/osdb.py
codefast/io/sqlite.py
codefast/models/__init__.py
codefast/models/date.py
codefast/os/__init__.py
codefast/patterns/__init__.py
codefast/patterns/factory_method.py
codefast/patterns/observer.py
codefast/patterns/pipeline.py
codefast/patterns/pubsub.py
codefast/patterns/responsibility_chain.py
codefast/patterns/singleton.py
codefast/types/__init__.py
codefas-25.4.7.16.22.dist-info/LICENSE
codefas-25.4.7.16.22.dist-info/METADATA
codefas-25.4.7.16.22.dist-info/WHEEL
codefas-25.4.7.16.22.dist-info/top_level.txt
codefas-25.4.7.16.22.dist-info/RECORD
