Metadata-Version: 2.1
Name: codefas
Version: 25.4.7.16.22
Summary: A package for faster coding.
Home-page: https://github.com/ultrasev
Author: ultrasev
Author-email: i@ultrasev.com
Keywords: coding,development,tools
Classifier: Development Status :: 4 - Beta
Classifier: Intended Audience :: Developers
Classifier: Programming Language :: Python :: 3
Classifier: Programming Language :: Python :: 3.7
Classifier: Programming Language :: Python :: 3.8
Classifier: Programming Language :: Python :: 3.9
Classifier: Programming Language :: Python :: 3.10
Classifier: Programming Language :: Python :: 3.11
Classifier: License :: OSI Approved :: MIT License
Classifier: Operating System :: OS Independent
Classifier: Topic :: Software Development :: Libraries :: Python Modules
Requires-Python: >=3.7
License-File: LICENSE
Requires-Dist: colorlog>=6.0.0
Requires-Dist: lxml>=4.9.0
Requires-Dist: requests>=2.28.0
Requires-Dist: tqdm>=4.65.0
Requires-Dist: smart-open>=6.0.0
Requires-Dist: beautifulsoup4>=4.11.0
Requires-Dist: arrow>=1.2.0
Requires-Dist: termcolor>=2.0.0
Requires-Dist: pycryptodome>=3.17.0
Requires-Dist: requests-toolbelt>=1.0.0
Requires-Dist: tenacity>=8.0.0
Requires-Dist: aiohttp>=3.8.0
Requires-Dist: pydantic>=2.9.0
Requires-Dist: loguru>=0.7.0
Requires-Dist: httpx>=0.25.0
